fastapi_opinionated_eventbus/__init__.py
fastapi_opinionated_eventbus/events.py
fastapi_opinionated_eventbus/helpers.py
fastapi_opinionated_eventbus/plugin.py
fastapi_opinionated_eventbus-0.1.1.dist-info/METADATA
fastapi_opinionated_eventbus-0.1.1.dist-info/WHEEL
fastapi_opinionated_eventbus-0.1.1.dist-info/RECORD
