Metadata-Version: 2.3
Name: fastapi-opinionated-eventbus
Version: 0.1.1
Summary: 
Author: Azzarnuji
Author-email: azzarnuzy93@gmail.com
Requires-Python: >=3.12
Classifier: Programming Language :: Python :: 3
Classifier: Programming Language :: Python :: 3.12
Classifier: Programming Language :: Python :: 3.13
Requires-Dist: fastapi-opinionated-core (>=0.1.2,<0.2.0)
